squash_tf/__init__.py
squash_tf/squashTfRobotframeworkRunnerParameter.py
squash_tf_services-2.0.0.dist-info/LICENSE
squash_tf_services-2.0.0.dist-info/METADATA
squash_tf_services-2.0.0.dist-info/WHEEL
squash_tf_services-2.0.0.dist-info/top_level.txt
squash_tf_services-2.0.0.dist-info/RECORD
