Metadata-Version: 2.1
Name: squash-tf-services
Version: 2.0.0
Summary: This package allows to use test parameters from Squash directly in tests.
Home-page: https://squash-tf.readthedocs.io/projects/runner-robotframework/en/doc-stable/tf-param-service.html
Author: Henix
Author-email: faq-python@squashtest.com
License: License :: OSI Approved :: Apache Software License
Keywords: automated_testing robotframework SquashTM Squash TF
Platform: UNKNOWN
Classifier: Programming Language :: Python :: 3
Classifier: License :: OSI Approved :: Apache Software License
License-File: LICENSE
